<annotations>
  <file>frame01968</file>
  <object>
    <name>person</name>
    <bndbox>
      <xmin>957.5564</xmin>
      <ymin>523.1064</ymin>
      <xmax>1069.3335</xmax>
      <ymax>954.1091</ymax>
    </bndbox>
  </object>
  <object>
    <name>person</name>
    <bndbox>
      <xmin>994.5478</xmin>
      <ymin>519.2061</ymin>
      <xmax>1066.8121</xmax>
      <ymax>667.7309</ymax>
    </bndbox>
  </object>
  <object>
    <name>person</name>
    <bndbox>
      <xmin>1000.848</xmin>
      <ymin>576.436</ymin>
      <xmax>1062.0321</xmax>
      <ymax>662.7206</ymax>
    </bndbox>
  </object>
  <object>
    <name>person</name>
    <bndbox>
      <xmin>955.125</xmin>
      <ymin>522.0132</ymin>
      <xmax>1051.7239</xmax>
      <ymax>680.9843</ymax>
    </bndbox>
  </object>
  <object>
    <name>person</name>
    <bndbox>
      <xmin>989.37836</xmin>
      <ymin>529.37445</ymin>
      <xmax>1065.7191</xmax>
      <ymax>777.5188</ymax>
    </bndbox>
  </object>
  <object>
    <name>person</name>
    <bndbox>
      <xmin>939.2356</xmin>
      <ymin>542.2094</ymin>
      <xmax>1040.6766</xmax>
      <ymax>859.34827</ymax>
    </bndbox>
  </object>
  <object>
    <name>surfboard</name>
    <bndbox>
      <xmin>947.32526</xmin>
      <ymin>516.693</ymin>
      <xmax>1065.6661</xmax>
      <ymax>945.05725</ymax>
    </bndbox>
  </object>
  <object>
    <name>skateboard</name>
    <bndbox>
      <xmin>939.73236</xmin>
      <ymin>514.25446</ymin>
      <xmax>1064.9948</xmax>
      <ymax>952.86237</ymax>
    </bndbox>
  </object>
  <object>
    <name>snowboard</name>
    <bndbox>
      <xmin>947.32526</xmin>
      <ymin>516.693</ymin>
      <xmax>1065.6661</xmax>
      <ymax>945.05725</ymax>
    </bndbox>
  </object>
</annotations>
