<annotations>
  <file>frame01213</file>
  <object>
    <name>person</name>
    <bndbox>
      <xmin>708.9121</xmin>
      <ymin>448.39044</ymin>
      <xmax>761.3361</xmax>
      <ymax>512.2583</ymax>
    </bndbox>
  </object>
  <object>
    <name>person</name>
    <bndbox>
      <xmin>726.80914</xmin>
      <ymin>446.89508</ymin>
      <xmax>758.54095</xmax>
      <ymax>498.3974</ymax>
    </bndbox>
  </object>
  <object>
    <name>person</name>
    <bndbox>
      <xmin>731.1726</xmin>
      <ymin>455.69815</ymin>
      <xmax>764.62054</xmax>
      <ymax>511.7147</ymax>
    </bndbox>
  </object>
  <object>
    <name>person</name>
    <bndbox>
      <xmin>706.39984</xmin>
      <ymin>448.01508</ymin>
      <xmax>751.77716</xmax>
      <ymax>487.63422</ymax>
    </bndbox>
  </object>
  <object>
    <name>person</name>
    <bndbox>
      <xmin>726.1841</xmin>
      <ymin>477.03796</ymin>
      <xmax>760.46924</xmax>
      <ymax>515.1955</ymax>
    </bndbox>
  </object>
  <object>
    <name>person</name>
    <bndbox>
      <xmin>704.391</xmin>
      <ymin>455.4229</ymin>
      <xmax>739.82526</xmax>
      <ymax>510.96686</ymax>
    </bndbox>
  </object>
  <object>
    <name>bird</name>
    <bndbox>
      <xmin>709.4739</xmin>
      <ymin>447.16528</ymin>
      <xmax>760.93823</xmax>
      <ymax>513.07983</ymax>
    </bndbox>
  </object>
  <object>
    <name>bird</name>
    <bndbox>
      <xmin>726.80914</xmin>
      <ymin>446.89508</ymin>
      <xmax>758.54095</xmax>
      <ymax>498.3974</ymax>
    </bndbox>
  </object>
  <object>
    <name>horse</name>
    <bndbox>
      <xmin>708.5294</xmin>
      <ymin>449.4408</ymin>
      <xmax>761.3405</xmax>
      <ymax>513.04254</ymax>
    </bndbox>
  </object>
  <object>
    <name>dog</name>
    <bndbox>
      <xmin>708.5294</xmin>
      <ymin>449.4408</ymin>
      <xmax>761.3405</xmax>
      <ymax>513.04254</ymax>
    </bndbox>
  </object>
  <object>
    <name>kite</name>
    <bndbox>
      <xmin>708.5294</xmin>
      <ymin>449.4408</ymin>
      <xmax>761.3405</xmax>
      <ymax>513.04254</ymax>
    </bndbox>
  </object>
  <object>
    <name>motorcycle</name>
    <bndbox>
      <xmin>720.7097</xmin>
      <ymin>451.59796</ymin>
      <xmax>760.47943</xmax>
      <ymax>512.24146</ymax>
    </bndbox>
  </object>
  <object>
    <name>skateboard</name>
    <bndbox>
      <xmin>719.5333</xmin>
      <ymin>454.04843</ymin>
      <xmax>761.2775</xmax>
      <ymax>510.69946</ymax>
    </bndbox>
  </object>
  <object>
    <name>chair</name>
    <bndbox>
      <xmin>719.5333</xmin>
      <ymin>454.04843</ymin>
      <xmax>761.2775</xmax>
      <ymax>510.69946</ymax>
    </bndbox>
  </object>
</annotations>
