<annotations>
  <file>frame02310</file>
  <object>
    <name>traffic light</name>
    <bndbox>
      <xmin>311.14188</xmin>
      <ymin>14.907106</ymin>
      <xmax>331.95953</xmax>
      <ymax>34.024555</ymax>
    </bndbox>
  </object>
  <object>
    <name>traffic light</name>
    <bndbox>
      <xmin>159.18404</xmin>
      <ymin>13.782986</ymin>
      <xmax>193.14055</xmax>
      <ymax>39.693535</ymax>
    </bndbox>
  </object>
  <object>
    <name>bed</name>
    <bndbox>
      <xmin>0.0</xmin>
      <ymin>0.0</ymin>
      <xmax>632.47076</xmax>
      <ymax>473.5749</ymax>
    </bndbox>
  </object>
  <object>
    <name>bed</name>
    <bndbox>
      <xmin>0.0</xmin>
      <ymin>240.98111</ymin>
      <xmax>640.2</xmax>
      <ymax>709.65027</ymax>
    </bndbox>
  </object>
  <object>
    <name>bed</name>
    <bndbox>
      <xmin>321.22763</xmin>
      <ymin>248.62967</ymin>
      <xmax>807.0542</xmax>
      <ymax>719.8379</ymax>
    </bndbox>
  </object>
  <object>
    <name>bed</name>
    <bndbox>
      <xmin>0.0</xmin>
      <ymin>480.0</ymin>
      <xmax>639.67896</xmax>
      <ymax>958.0531</ymax>
    </bndbox>
  </object>
  <object>
    <name>bed</name>
    <bndbox>
      <xmin>329.85077</xmin>
      <ymin>480.0</ymin>
      <xmax>960.2</xmax>
      <ymax>955.2015</ymax>
    </bndbox>
  </object>
  <object>
    <name>bed</name>
    <bndbox>
      <xmin>640.0</xmin>
      <ymin>480.0</ymin>
      <xmax>1280.2</xmax>
      <ymax>960.0</ymax>
    </bndbox>
  </object>
  <object>
    <name>person</name>
    <bndbox>
      <xmin>878.24756</xmin>
      <ymin>201.10175</ymin>
      <xmax>903.72437</xmax>
      <ymax>227.79913</ymax>
    </bndbox>
  </object>
  <object>
    <name>person</name>
    <bndbox>
      <xmin>925.58093</xmin>
      <ymin>195.88919</ymin>
      <xmax>947.89874</xmax>
      <ymax>241.48705</ymax>
    </bndbox>
  </object>
  <object>
    <name>person</name>
    <bndbox>
      <xmin>1243.844</xmin>
      <ymin>337.62204</ymin>
      <xmax>1279.6091</xmax>
      <ymax>473.09195</ymax>
    </bndbox>
  </object>
  <object>
    <name>person</name>
    <bndbox>
      <xmin>881.4855</xmin>
      <ymin>202.15031</ymin>
      <xmax>901.9134</xmax>
      <ymax>225.91492</ymax>
    </bndbox>
  </object>
  <object>
    <name>person</name>
    <bndbox>
      <xmin>643.1309</xmin>
      <ymin>486.70474</ymin>
      <xmax>758.7342</xmax>
      <ymax>708.0998</ymax>
    </bndbox>
  </object>
  <object>
    <name>person</name>
    <bndbox>
      <xmin>239.80211</xmin>
      <ymin>569.7084</ymin>
      <xmax>316.82483</xmax>
      <ymax>656.06525</ymax>
    </bndbox>
  </object>
  <object>
    <name>person</name>
    <bndbox>
      <xmin>818.7534</xmin>
      <ymin>662.79877</ymin>
      <xmax>831.3959</xmax>
      <ymax>685.7466</ymax>
    </bndbox>
  </object>
  <object>
    <name>person</name>
    <bndbox>
      <xmin>463.6925</xmin>
      <ymin>777.02075</ymin>
      <xmax>476.9248</xmax>
      <ymax>800.47253</ymax>
    </bndbox>
  </object>
  <object>
    <name>couch</name>
    <bndbox>
      <xmin>0.0</xmin>
      <ymin>241.50024</ymin>
      <xmax>638.85504</xmax>
      <ymax>714.6444</ymax>
    </bndbox>
  </object>
  <object>
    <name>couch</name>
    <bndbox>
      <xmin>320.0</xmin>
      <ymin>480.19376</ymin>
      <xmax>960.2</xmax>
      <ymax>954.45483</ymax>
    </bndbox>
  </object>
  <object>
    <name>teddy bear</name>
    <bndbox>
      <xmin>0.0</xmin>
      <ymin>240.0</ymin>
      <xmax>640.2</xmax>
      <ymax>711.72266</ymax>
    </bndbox>
  </object>
  <object>
    <name>teddy bear</name>
    <bndbox>
      <xmin>645.1156</xmin>
      <ymin>483.8306</ymin>
      <xmax>756.91046</xmax>
      <ymax>621.417</ymax>
    </bndbox>
  </object>
  <object>
    <name>teddy bear</name>
    <bndbox>
      <xmin>303.19388</xmin>
      <ymin>485.87863</ymin>
      <xmax>633.6312</xmax>
      <ymax>862.35767</ymax>
    </bndbox>
  </object>
  <object>
    <name>teddy bear</name>
    <bndbox>
      <xmin>320.0</xmin>
      <ymin>480.19376</ymin>
      <xmax>960.2</xmax>
      <ymax>954.45483</ymax>
    </bndbox>
  </object>
  <object>
    <name>teddy bear</name>
    <bndbox>
      <xmin>376.3034</xmin>
      <ymin>485.7644</ymin>
      <xmax>896.2837</xmax>
      <ymax>749.7433</ymax>
    </bndbox>
  </object>
  <object>
    <name>broccoli</name>
    <bndbox>
      <xmin>377.08444</xmin>
      <ymin>597.704</ymin>
      <xmax>495.3465</xmax>
      <ymax>715.1082</ymax>
    </bndbox>
  </object>
  <object>
    <name>cat</name>
    <bndbox>
      <xmin>0.0</xmin>
      <ymin>240.98111</ymin>
      <xmax>640.2</xmax>
      <ymax>709.65027</ymax>
    </bndbox>
  </object>
  <object>
    <name>cat</name>
    <bndbox>
      <xmin>329.85077</xmin>
      <ymin>480.0</ymin>
      <xmax>960.2</xmax>
      <ymax>955.2015</ymax>
    </bndbox>
  </object>
  <object>
    <name>bird</name>
    <bndbox>
      <xmin>654.76953</xmin>
      <ymin>482.04285</ymin>
      <xmax>753.5624</xmax>
      <ymax>617.1031</ymax>
    </bndbox>
  </object>
  <object>
    <name>bird</name>
    <bndbox>
      <xmin>818.9635</xmin>
      <ymin>663.2111</ymin>
      <xmax>831.3783</xmax>
      <ymax>685.70953</ymax>
    </bndbox>
  </object>
  <object>
    <name>bird</name>
    <bndbox>
      <xmin>644.35913</xmin>
      <ymin>484.51398</ymin>
      <xmax>756.17017</xmax>
      <ymax>622.6783</ymax>
    </bndbox>
  </object>
  <object>
    <name>bird</name>
    <bndbox>
      <xmin>1066.8052</xmin>
      <ymin>400.02582</ymin>
      <xmax>1087.6757</xmax>
      <ymax>426.39032</ymax>
    </bndbox>
  </object>
  <object>
    <name>bird</name>
    <bndbox>
      <xmin>240.45813</xmin>
      <ymin>572.02576</ymin>
      <xmax>317.26917</xmax>
      <ymax>655.97095</ymax>
    </bndbox>
  </object>
  <object>
    <name>bird</name>
    <bndbox>
      <xmin>253.58449</xmin>
      <ymin>583.0545</ymin>
      <xmax>297.18246</xmax>
      <ymax>653.8265</ymax>
    </bndbox>
  </object>
  <object>
    <name>bird</name>
    <bndbox>
      <xmin>818.7534</xmin>
      <ymin>662.79877</ymin>
      <xmax>831.3959</xmax>
      <ymax>685.7466</ymax>
    </bndbox>
  </object>
  <object>
    <name>bird</name>
    <bndbox>
      <xmin>818.40857</xmin>
      <ymin>662.1938</ymin>
      <xmax>830.8085</xmax>
      <ymax>685.30634</ymax>
    </bndbox>
  </object>
  <object>
    <name>sheep</name>
    <bndbox>
      <xmin>239.54349</xmin>
      <ymin>563.536</ymin>
      <xmax>320.25082</xmax>
      <ymax>660.2668</ymax>
    </bndbox>
  </object>
  <object>
    <name>sheep</name>
    <bndbox>
      <xmin>265.0682</xmin>
      <ymin>586.8784</ymin>
      <xmax>316.7822</xmax>
      <ymax>656.1659</ymax>
    </bndbox>
  </object>
  <object>
    <name>cow</name>
    <bndbox>
      <xmin>239.54349</xmin>
      <ymin>563.536</ymin>
      <xmax>320.25082</xmax>
      <ymax>660.2668</ymax>
    </bndbox>
  </object>
  <object>
    <name>dog</name>
    <bndbox>
      <xmin>240.45813</xmin>
      <ymin>572.02576</ymin>
      <xmax>317.26917</xmax>
      <ymax>655.97095</ymax>
    </bndbox>
  </object>
  <object>
    <name>dog</name>
    <bndbox>
      <xmin>320.0</xmin>
      <ymin>480.19376</ymin>
      <xmax>960.2</xmax>
      <ymax>954.45483</ymax>
    </bndbox>
  </object>
  <object>
    <name>horse</name>
    <bndbox>
      <xmin>240.45813</xmin>
      <ymin>572.02576</ymin>
      <xmax>317.26917</xmax>
      <ymax>655.97095</ymax>
    </bndbox>
  </object>
  <object>
    <name>bear</name>
    <bndbox>
      <xmin>324.2224</xmin>
      <ymin>481.59067</ymin>
      <xmax>960.2</xmax>
      <ymax>948.0381</ymax>
    </bndbox>
  </object>
  <object>
    <name>elephant</name>
    <bndbox>
      <xmin>320.0</xmin>
      <ymin>480.19376</ymin>
      <xmax>960.2</xmax>
      <ymax>954.45483</ymax>
    </bndbox>
  </object>
  <object>
    <name>sandwich</name>
    <bndbox>
      <xmin>324.0973</xmin>
      <ymin>480.0</ymin>
      <xmax>960.2</xmax>
      <ymax>950.00806</ymax>
    </bndbox>
  </object>
  <object>
    <name>potted plant</name>
    <bndbox>
      <xmin>326.52023</xmin>
      <ymin>728.2647</ymin>
      <xmax>441.46082</xmax>
      <ymax>954.4647</ymax>
    </bndbox>
  </object>
</annotations>
